[{"tags":["test-dolphin-1"],"result":"ok","needle":"dolphin-131B1","area":[{"h":274,"result":"ok","similarity":98,"w":528,"diff":"dolphin-1-dolphin-131B1-diff0.png","y":"3","x":"203"}],"screenshot":"dolphin-1.png"},{"screenshot":"dolphin-2.png","area":[{"result":"ok","similarity":99,"w":59,"x":"0","diff":"dolphin-2-reboot_after_install-131M4-diff0.png","y":"736","h":32},{"h":594,"diff":"dolphin-2-reboot_after_install-131M4-diff1.png","x":"629","y":"0","result":"ok","similarity":99,"w":389},{"h":189,"diff":"dolphin-2-reboot_after_install-131M4-diff2.png","y":"54","x":"63","similarity":98,"result":"ok","w":444}],"result":"ok","needle":"reboot_after_install-131M4","tags":["test-consoletest_finish-1"]}]